Workbook

Sheet Base e QC
A1: # | B1: Loja | C1: Index | D1: ID do Anúncio | E1: Nome do Anúncio | F1: Impressões | G1: Cliques | H1: CTR | I1: Conversões | J1: Custo por Conversão | K1: Taxa de Conversão | L1: Itens Vendidos | M1: GMV | N1: Despesas | O1: ACOS | P1: Categoria | Q1: Tamanho | R1: Qtd | S1: % Lucro Médio P | T1: lucro liquido | U1: % Lucro | V1: índice
A2: 28 | B2: 1 | C2: A4+A3 | D2: 21997807147 | E2: Kit 6 Bases de Corte (3 un A3 + 3 unidades A4 Paisagem) + 1 Refil de cola Universal 50g | F2: 167 | G2: 0 | H2: 0 | I2: 0 | J2: 0 | K2: 0 | L2: 0 | M2: 0 | N2: 0 | O2: 0 | P2: Base de Corte | Q2: A4 + A3 | R2: 6 | S2: 0.3 | T2: =+S2*M2 -> 0 | U2: =+T2/M2 -> #DIV/0! | V2: =+T2*U2 -> #DIV/0!
A3: 6 | B3: 1 | C3: Base 30x30 | D3: 23092653904 | E3: Base de Corte 30x30 Transparente COMPATIVEL Silhouette Cameo 1, 2, 3 4, 5 Plus e Pro - Com Cola | F3: 5958 | G3: 108 | H3: 0.0181 | I3: 12 | J3: 2.57 | K3: 0.1111 | L3: 14 | M3: 460.6 | N3: 30.84 | O3: 0.0669 | P3: Base de Corte | Q3: 30x30 | R3: 1 | S3: 0.35413153 | T3: =+S3*M3 -> 163.11298 | U3: =+T3/M3 -> 0.35413153 | V3: =+T3*U3 -> 57.763451
A4: 7 | B4: 1 | C4: Base 30x30 | D4: 22393068915 | E4: Base de Corte 30x30 Transparente Compativel Silhouette Cameo 1, 2, 3 e 4 Cola Refil 50g | F4: 6299 | G4: 49 | H4: 0.0078 | I4: 6 | J4: 3.17 | K4: 0.1224 | L4: 6 | M4: 349.4 | N4: 19 | O4: 0.0544 | P4: Base de Corte | Q4: 30x30 | R4: 1 | S4: 0.35413153 | T4: =+S4*M4 -> 123.73356 | U4: =+T4/M4 -> 0.35413153 | V4: =+T4*U4 -> 43.817955
A5: 18 | B5: 1 | C5: Base 30x30 | D5: 23897145567 | E5: KIT 2 Base de Corte 30x30 Transparente COMPATIVEL Silhouette Cameo 2, 3 - Com Cola | F5: 10249 | G5: 106 | H5: 0.0103 | I5: 5 | J5: 7.83 | K5: 0.0472 | L5: 6 | M5: 399.4 | N5: 39.13 | O5: 0.098 | P5: Base de Corte | Q5: 30x30 | R5: 2 | S5: 0.35602573 | T5: =+S5*M5 -> 142.19667 | U5: =+T5/M5 -> 0.35602573 | V5: =+T5*U5 -> 50.625674
A6: 19 | B6: 1 | C6: Base 30x30 | D6: 23092653852 | E6: Kit 2 Base de Corte 30x30 Transparente Compativel Silhouette, Cameo - Com Cola Alta Fixação | F6: 10452 | G6: 151 | H6: 0.0144 | I6: 25 | J6: 3.04 | K6: 0.1656 | L6: 26 | M6: 1297.4 | N6: 75.98 | O6: 0.0586 | P6: Base de Corte | Q6: 30x30 | R6: 2 | S6: 0.35602573 | T6: =+S6*M6 -> 461.90778 | U6: =+T6/M6 -> 0.35602573 | V6: =+T6*U6 -> 164.45105
A7: 23 | B7: 1 | C7: Base 30x30 | D7: 17507436448 | E7: Kit 2 Bases De Corte 30x30 Compativel Silhouette Cameo com Cola | F7: 7333 | G7: 77 | H7: 0.0105 | I7: 5 | J7: 5.12 | K7: 0.0649 | L7: 5 | M7: 349.5 | N7: 25.59 | O7: 0.0732 | P7: Base de Corte | Q7: 30x30 | R7: 2 | S7: 0.35602573 | T7: =+S7*M7 -> 124.43099 | U7: =+T7/M7 -> 0.35602573 | V7: =+T7*U7 -> 44.300634
A8: 26 | B8: 1 | C8: Base 30x30 | D8: 19699244794 | E8: Kit 4 Bases de Corte 30x30 Transparente + 1 Cola de Reposição 50g - Para Silhouette Cameo Compatível | F8: 4968 | G8: 52 | H8: 0.0105 | I8: 5 | J8: 6.86 | K8: 0.0962 | L8: 5 | M8: 597.5 | N8: 34.3 | O8: 0.0574 | P8: Base de Corte | Q8: 30x30 | R8: 4 | S8: 0.37342069 | T8: =+S8*M8 -> 223.11886 | U8: =+T8/M8 -> 0.37342069 | V8: =+T8*U8 -> 83.3172
A9: 40 | B9: 2 | C9: Base 30x30 | D9: 20897672485 | E9: 2 Base de Corte 30x30 Transparente Para Silhouette Cameo, Cameo 2 3 4, 4 Plus e 4 Pro - Com e Sem Cola [3] | F9: 75988 | G9: 1544 | H9: 2.03% | I9: 200 | J9: 4.04 | K9: 12.95% | L9: 206 | M9: 10612.52 | N9: 808.29 | O9: 7.62% | P9: Base de Corte | Q9: 30x30 | R9: 2 | S9: 0.35602573 | T9: =+S9*M9 -> 3778.3301 | U9: =+T9/M9 -> 0.35602573 | V9: =+T9*U9 -> 1345.1827
A10: 44 | B10: 2 | C10: Base 30x30 | D10: 21397167338 | E10: 1 Base de Corte 30x30 Para Silhouette Cameo, Cameo 1 2 3 4, 4 Plus e 4 Pro - Versão Com Cola e Sem Cola - 0,40mm [5] | F10: 34950 | G10: 818 | H10: 2.34% | I10: 121 | J10: 2.04 | K10: 14.79% | L10: 125 | M10: 3726.5 | N10: 246.36 | O10: 6.61% | P10: Base de Corte | Q10: 30x30 | R10: 1 | S10: 0.35413153 | T10: =+S10*M10 -> 1319.6712 | U10: =+T10/M10 -> 0.35413153 | V10: =+T10*U10 -> 467.33717
A11: 51 | B11: 2 | C11: Base 30x30 | D11: 22397598129 | E11: Base de corte 30x30 Silhouette Portrait 1, 2, e 3 Transparente Com e Sem Cola [2] | F11: 15990 | G11: 303 | H11: 1.89% | I11: 25 | J11: 3.75 | K11: 8.25% | L11: 25 | M11: 846.5 | N11: 93.83 | O11: 11.08% | P11: Base de Corte | Q11: 30x30 | R11: 1 | S11: 0.35413153 | T11: =+S11*M11 -> 299.77234 | U11: =+T11/M11 -> 0.35413153 | V11: =+T11*U11 -> 106.15884
A12: 55 | B12: 2 | C12: Base 30x30 | D12: 23192993710 | E12: Kit 2 Base de Corte 30x30 Transparente + 1 Cola Refil Base 50g - Compativel Silhouette Portrait, Portrait 2, 3 [3] | F12: 11790 | G12: 156 | H12: 1.32% | I12: 22 | J12: 4.48 | K12: 14.10% | L12: 22 | M12: 1362.3 | N12: 98.59 | O12: 7.24% | P12: Base de Corte | Q12: 30x30 | R12: 2 | S12: 0.35602573 | T12: =+S12*M12 -> 485.01385 | U12: =+T12/M12 -> 0.35602573 | V12: =+T12*U12 -> 172.67741
A13: 58 | B13: 2 | C13: Base 30x30 | D13: 23597490298 | E13: kit 4 Esteira de Corte 30x30 Transparente + 1 Cola Base 50g Compativel Silhouette Portrait 2 e 3 Cameo [3] | F13: 11076 | G13: 153 | H13: 1.38% | I13: 13 | J13: 7.02 | K13: 8.50% | L13: 13 | M13: 1175.8 | N13: 91.28 | O13: 7.76% | P13: Base de Corte | Q13: 30x30 | R13: 4 | S13: 0.37342069 | T13: =+S13*M13 -> 439.06805 | U13: =+T13/M13 -> 0.37342069 | V13: =+T13*U13 -> 163.95709
A14: 12 | B14: 1 | C14: Base 30x30 CM | D14: 13869340936 | E14: Base de Corte C/Cola 30x30 Brother Scanncut - Cm300 (Espessura: 30mm) | F14: 8898 | G14: 211 | H14: 0.0237 | I14: 17 | J14: 4.12 | K14: 0.0806 | L14: 18 | M14: 664.2 | N14: 70 | O14: 0.1054 | P14: Base de Corte | Q14: 30x30 Scanncut | R14: 1 | S14: 0.3887618 | T14: =+S14*M14 -> 258.21559 | U14: =+T14/M14 -> 0.3887618 | V14: =+T14*U14 -> 100.38436
A15: 15 | B15: 1 | C15: Base 30x30 CM | D15: 15037739365 | E15: Brother ScanNCut - Base de Corte 30x30cm - Compatível com CM300, CM550 e CM650 | F15: 7279 | G15: 176 | H15: 0.0242 | I15: 9 | J15: 4.23 | K15: 0.0511 | L15: 9 | M15: 331.2 | N15: 38.04 | O15: 0.1148 | P15: Base de Corte | Q15: 30x30 Scanncut | R15: 1 | S15: 0.3887618 | T15: =+S15*M15 -> 128.75791 | U15: =+T15/M15 -> 0.3887618 | V15: =+T15*U15 -> 50.056156
A16: 17 | B16: 1 | C16: Base 30x30 CM | D16: 15833567190 | E16: Esteira De Corte 30x30 Para Brother Scanncut CM300, CM550 e CM650 - Envio Imediato! | F16: 30225 | G16: 1114 | H16: 0.0369 | I16: 62 | J16: 2.44 | K16: 0.0557 | L16: 64 | M16: 2315.9 | N16: 151.02 | O16: 0.0652 | P16: Base de Corte | Q16: 30x30 Scanncut | R16: 1 | S16: 0.3887618 | T16: =+S16*M16 -> 900.33345 | U16: =+T16/M16 -> 0.3887618 | V16: =+T16*U16 -> 350.01525
A17: 42 | B17: 2 | C17: Base 30x30 SDX | D17: 22792913222 | E17: 1 Base de Corte 30x30 Com Cola para ScanNcut SDX 85, 125 e 225 - Envio Expresso [3] | F17: 36365 | G17: 928 | H17: 2.55% | I17: 59 | J17: 4.67 | K17: 6.36% | L17: 62 | M17: 4001.69 | N17: 275.75 | O17: 6.89% | P17: Base de Corte | Q17: 30x30 SDX | R17: 1 | S17: 0.46083641 | T17: =+S17*M17 -> 1844.1245 | U17: =+T17/M17 -> 0.46083641 | V17: =+T17*U17 -> 849.8397
A18: 8 | B18: 1 | C18: Base 30x60 | D18: 11714995653 | E18: Base De Corte 30x60 Com Cola Compatível com Silhouette Cameo - Plotters Qualidade Original | F18: 8226 | G18: 185 | H18: 0.0225 | I18: 11 | J18: 4.4 | K18: 0.0595 | L18: 11 | M18: 512.9 | N18: 48.37 | O18: 0.0943 | P18: Base de Corte | Q18: 30x60 | R18: 1 | S18: 0.31733086 | T18: =+S18*M18 -> 162.759 | U18: =+T18/M18 -> 0.31733086 | V18: =+T18*U18 -> 51.648454
A19: 10 | B19: 1 | C19: Base 30x60 | D19: 22891613667 | E19: Base de Corte 30x60 Para Silhouette Cameo, Cameo 2 3 4 e 4 Plus - Com Cola e Sem Cola - 40mm e 30mm | F19: 7003 | G19: 87 | H19: 0.0124 | I19: 5 | J19: 5.23 | K19: 0.0575 | L19: 5 | M19: 229.3 | N19: 26.13 | O19: 0.114 | P19: Base de Corte | Q19: 30x60 | R19: 1 | S19: 0.31733086 | T19: =+S19*M19 -> 72.763967 | U19: =+T19/M19 -> 0.31733086 | V19: =+T19*U19 -> 23.090252
A20: 14 | B20: 1 | C20: Base 30x60 | D20: 15657461060 | E20: Base de Corte para Silhouette Cameo Bannercut 30x60 Com Cola Alta fixação e durabilidade | F20: 7543 | G20: 127 | H20: 0.0168 | I20: 8 | J20: 3.35 | K20: 0.063 | L20: 8 | M20: 367.2 | N20: 26.81 | O20: 0.073 | P20: Base de Corte | Q20: 30x60 | R20: 1 | S20: 0.31733086 | T20: =+S20*M20 -> 116.52389 | U20: =+T20/M20 -> 0.31733086 | V20: =+T20*U20 -> 36.976627
A21: 27 | B21: 1 | C21: Base 30x60 | D21: 22298698288 | E21: KIT 5 placa - Base de Corte 30x60 - com Cola - compatível mesa Transparente | F21: 2578 | G21: 18 | H21: 0.007 | I21: 0 | J21: 0 | K21: 0 | L21: 0 | M21: 0 | N21: 10.18 | O21: 0 | P21: Base de Corte | Q21: 30x60 | R21: 5 | S21: 0.29684227 | T21: =+S21*M21 -> 0 | U21: =+T21/M21 -> #DIV/0! | V21: =+T21*U21 -> #DIV/0!
A22: 52 | B22: 2 | C22: Base 30x60 | D22: 22392895533 | E22: Base de Corte 30x60 Para Cameo Silhouette - Espessura Original - Corte Com Precisão - Com Cola [3] | F22: 14429 | G22: 249 | H22: 1.73% | I22: 22 | J22: 5 | K22: 8.84% | L22: 25 | M22: 1325.74 | N22: 110.08 | O22: 8.30% | P22: Base de Corte | Q22: 30x60 | R22: 1 | S22: 0.31733086 | T22: =+S22*M22 -> 420.69822 | U22: =+T22/M22 -> 0.31733086 | V22: =+T22*U22 -> 133.50053
A23: 57 | B23: 2 | C23: Base 30x60 | D23: 22392890747 | E23: 1 Esteira Base de Corte 30x60 Para Plotters Cameo Silhouette [2] | F23: 11393 | G23: 250 | H23: 2.19% | I23: 13 | J23: 4.54 | K23: 5.20% | L23: 13 | M23: 582.86 | N23: 58.99 | O23: 10.12% | P23: Base de Corte | Q23: 30x60 | R23: 1 | S23: 0.31733086 | T23: =+S23*M23 -> 184.95947 | U23: =+T23/M23 -> 0.31733086 | V23: =+T23*U23 -> 58.693347
A24: 9 | B24: 1 | C24: Base 30x60 SDX | D24: 15250252385 | E24: Base de Corte 30x60 Com Cola para Brother SDX 85, SDX 125 e SDX 225 - Envio Expresso | F24: 18785 | G24: 567 | H24: 0.0302 | I24: 36 | J24: 3.45 | K24: 0.0635 | L24: 38 | M24: 1640.2 | N24: 124.13 | O24: 0.0757 | P24: Base de Corte | Q24: 30x60 SDX | R24: 1 | S24: 0.33723319 | T24: =+S24*M24 -> 553.12988 | U24: =+T24/M24 -> 0.33723319 | V24: =+T24*U24 -> 186.53375
A25: 77 | B25: 3 | C25: Base 30x60 SDX | D25: 23329850370 | E25: Base de Corte Sem Cola 30x60 Para Brother SDX 85, 125 e 225 Espessura original Rigidez [3] | F25: 9349 | G25: 236 | H25: 2.52% | I25: 13 | J25: 3.99 | K25: 0.0551 | L25: 13 | M25: 713.12 | N25: 51.83 | O25: 0.0727 | P25: Base de Corte | Q25: 30x60 SDX Sem Cola | R25: 1 | S25: 0.31108802 | T25: =+S25*M25 -> 221.84309 | U25: =+T25/M25 -> 0.31108802 | V25: =+T25*U25 -> 69.012727
A26: 62 | B26: 2 | C26: Base 90x60 | D26: 22692878658 | E26: Base de corte 90x60 P/plotters Profissionais Silhouete Cameo 4, Cameo 4 Plus e Cameo Pro e outros modelos [3] | F26: 8148 | G26: 229 | H26: 2.81% | I26: 5 | J26: 7.17 | K26: 2.18% | L26: 5 | M26: 397.9 | N26: 35.84 | O26: 9.01% | P26: Base de Corte | Q26: 60x90 | R26: 1 | S26: 0.3421049 | T26: =+S26*M26 -> 136.12354 | U26: =+T26/M26 -> 0.3421049 | V26: =+T26*U26 -> 46.568529
A27: 4 | B27: 1 | C27: Base A3 | D27: 17936580203 | E27: 2 Bases de Corte Para Silhouette Cameo A3 Com Cola | F27: 5968 | G27: 74 | H27: 0.0124 | I27: 6 | J27: 5.19 | K27: 0.0811 | L27: 6 | M27: 401.4 | N27: 31.15 | O27: 0.0776 | P27: Base de Corte | Q27: A3 | R27: 2 | S27: 0.38135257 | T27: =+S27*M27 -> 153.07492 | U27: =+T27/M27 -> 0.38135257 | V27: =+T27*U27 -> 58.375515
A28: 5 | B28: 1 | C28: Base A3 | D28: 22698704717 | E28: 4 bases de Corte Cameo A3 Com Cola - Plotter Silhouette Qualidade Original Alta rigidez | F28: 5536 | G28: 40 | H28: 0.0072 | I28: 0 | J28: 0 | K28: 0 | L28: 0 | M28: 0 | N28: 3.34 | O28: 0 | P28: Base de Corte | Q28: A3 | R28: 4 | S28: 0.34723323 | T28: =+S28*M28 -> 0 | U28: =+T28/M28 -> #DIV/0! | V28: =+T28*U28 -> #DIV/0!
A29: 50 | B29: 2 | C29: Base A3 | D29: 23092924234 | E29: 1 Base de Corte A3 Branca Para Plotters Cameo Silhouette E Outros Modelos Confira - Com Cola [2] | F29: 17819 | G29: 339 | H29: 1.90% | I29: 35 | J29: 3.23 | K29: 10.32% | L29: 39 | M29: 1372.1 | N29: 113 | O29: 8.24% | P29: Base de Corte | Q29: A3 | R29: 1 | S29: 0.38388479 | T29: =+S29*M29 -> 526.72832 | U29: =+T29/M29 -> 0.38388479 | V29: =+T29*U29 -> 202.20299
A30: 73 | B30: 3 | C30: Base A3 | D30: 22629854054 | E30: Base de Corte A3 Com Cola Para Cameo Silhouette Artesanato - Compatibilidade Universal [4] | F30: 19342 | G30: 429 | H30: 2.22% | I30: 55 | J30: 2.84 | K30: 0.1282 | L30: 58 | M30: 1907.25 | N30: 156.36 | O30: 0.082 | P30: Base de Corte | Q30: A3 | R30: 1 | S30: 0.38388479 | T30: =+S30*M30 -> 732.16427 | U30: =+T30/M30 -> 0.38388479 | V30: =+T30*U30 -> 281.06673
A31: 1 | B31: 1 | C31: Base A4 | D31: 22398484368 | E31: 10 Mesa de corte base A4 - Alta Rigidez - resistente branco Poliester cristal | F31: 1302 | G31: 4 | H31: 0.0031 | I31: 1 | J31: 1.35 | K31: 0.25 | L31: 1 | M31: 77.9 | N31: 1.35 | O31: 0.0173 | P31: Base de Corte | Q31: A4 | R31: 10 | S31: 0.41310476 | T31: =+S31*M31 -> 32.180861 | U31: =+T31/M31 -> 0.41310476 | V31: =+T31*U31 -> 13.294067
A32: 2 | B32: 1 | C32: Base A4 | D32: 23697297381 | E32: 2 Base de Corte A4 Transparente +1 Cola Reposição Para Base 50g Para Silhouette Portrait 1,2, 3 e 4 Cameo 2 e 3 Com Cola | F32: 33399 | G32: 653 | H32: 0.0196 | I32: 90 | J32: 3.07 | K32: 0.1378 | L32: 90 | M32: 3828.68 | N32: 276.51 | O32: 0.0722 | P32: Base de Corte | Q32: A4 | R32: 2 | S32: 0.40691701 | T32: =+S32*M32 -> 1557.955 | U32: =+T32/M32 -> 0.40691701 | V32: =+T32*U32 -> 633.95838
A33: 3 | B33: 1 | C33: Base A4 | D33: 22694202713 | E33: 2 Bases de Corte A4 Compatível Silhouette Portrait 1,2,3 - Alta Rigidez Com Cola - Cameo | F33: 21575 | G33: 525 | H33: 0.0243 | I33: 51 | J33: 2.6 | K33: 0.0971 | L33: 51 | M33: 1791.68 | N33: 132.68 | O33: 0.0741 | P33: Base de Corte | Q33: A4 | R33: 2 | S33: 0.40691701 | T33: =+S33*M33 -> 729.06506 | U33: =+T33/M33 -> 0.40691701 | V33: =+T33*U33 -> 296.66897
A34: 11 | B34: 1 | C34: Base A4 | D34: 23597556517 | E34: Base de corte A4 Silhouette e Cameo 1 a 5 - Alta Durabilidade - Com ou Sem Cola | F34: 5422 | G34: 58 | H34: 0.0107 | I34: 7 | J34: 3.14 | K34: 0.1207 | L34: 8 | M34: 404.2 | N34: 21.95 | O34: 0.0543 | P34: Base de Corte | Q34: A4 | R34: 1 | S34: 0.38517754 | T34: =+S34*M34 -> 155.68876 | U34: =+T34/M34 -> 0.38517754 | V34: =+T34*U34 -> 59.967813
A35: 20 | B35: 1 | C35: Base A4 | D35: 20997495267 | E35: Kit 2 Base de Corte A4 Para Silhouette Portrait 2, 3 e 4 - Cameo, Cameo 2 e 3 - Com Cola | F35: 30716 | G35: 478 | H35: 0.0156 | I35: 57 | J35: 2.76 | K35: 0.1192 | L35: 58 | M35: 2304.6 | N35: 157.25 | O35: 0.0682 | P35: Base de Corte | Q35: A4 | R35: 2 | S35: 0.40691701 | T35: =+S35*M35 -> 937.78093 | U35: =+T35/M35 -> 0.40691701 | V35: =+T35*U35 -> 381.59901
A36: 21 | B36: 1 | C36: Base A4 | D36: 20997495263 | E36: Kit 2 Base de Corte A4 Transparente Silhouette Portrait, Portrait 2, 3 Cameo, Cameo 2 e 3 Com Cola | F36: 10484 | G36: 176 | H36: 0.0168 | I36: 21 | J36: 2.78 | K36: 0.1193 | L36: 21 | M36: 729.9 | N36: 58.43 | O36: 0.08 | P36: Base de Corte | Q36: A4 | R36: 2 | S36: 0.40691701 | T36: =+S36*M36 -> 297.00872 | U36: =+T36/M36 -> 0.40691701 | V36: =+T36*U36 -> 120.8579
A37: 25 | B37: 1 | C37: Base A4 | D37: 20997495265 | E37: Kit 4 Base de Corte A4 Transparente 1 Cola 50g Silhouette Portrait 2, 3 e 4 Papelaria e Escritório | F37: 43595 | G37: 665 | H37: 0.0153 | I37: 59 | J37: 5.04 | K37: 0.0887 | L37: 60 | M37: 4349 | N37: 297.24 | O37: 0.0683 | P37: Base de Corte | Q37: A4 | R37: 4 | S37: 0.37602001 | T37: =+S37*M37 -> 1635.311 | U37: =+T37/M37 -> 0.37602001 | V37: =+T37*U37 -> 614.90966
A38: 39 | B38: 2 | C38: Base A4 | D38: 23992823283 | E38: Kit 2 Bases A4 Transparentes Para Silhouette Portrait, Portrait 1, 2, 3 - Cameo, Cameo 2 e 3 - Com Cola [2] | F38: 158621 | G38: 3641 | H38: 2.30% | I38: 565 | J38: 2.25 | K38: 15.52% | L38: 575 | M38: 18534.15 | N38: 1269.58 | O38: 6.85% | P38: Base de Corte | Q38: A4 | R38: 2 | S38: 0.40691701 | T38: =+S38*M38 -> 7541.8608 | U38: =+T38/M38 -> 0.40691701 | V38: =+T38*U38 -> 3068.9114
A39: 41 | B39: 2 | C39: Base A4 | D39: 22893234695 | E39: Base de Corte Silhouette PORTRAIT e Silhouette CAMEO - Compatível Com Todos Os Modelos - COM COLA [3] | F39: 47196 | G39: 1130 | H39: 2.39% | I39: 119 | J39: 2.74 | K39: 10.53% | L39: 128 | M39: 3979.2 | N39: 325.83 | O39: 8.19% | P39: Base de Corte | Q39: A4 | R39: 1 | S39: 0.38517754 | T39: =+S39*M39 -> 1532.6985 | U39: =+T39/M39 -> 0.38517754 | V39: =+T39*U39 -> 590.36102
A40: 43 | B40: 2 | C40: Base A4 | D40: 23997480409 | E40: Base de corte A4 Silhouette Portrait 1, 2, 3 - Cameo Transparente Com e Sem Cola [3] | F40: 35186 | G40: 725 | H40: 2.06% | I40: 110 | J40: 2.37 | K40: 15.17% | L40: 111 | M40: 3825.21 | N40: 260.22 | O40: 6.80% | P40: Base de Corte | Q40: A4 | R40: 1 | S40: 0.38517754 | T40: =+S40*M40 -> 1473.385 | U40: =+T40/M40 -> 0.38517754 | V40: =+T40*U40 -> 567.51479
A41: 45 | B41: 2 | C41: Base A4 | D41: 19699242244 | E41: Kit 10 Bases de Corte A4 Transparente Compativel Silhouette Portrait 2, e 3 - Com Cola [2] | F41: 34214 | G41: 571 | H41: 1.67% | I41: 36 | J41: 9.84 | K41: 6.30% | L41: 36 | M41: 4601.24 | N41: 354.31 | O41: 7.70% | P41: Base de Corte | Q41: A4 | R41: 10 | S41: 0.41310476 | T41: =+S41*M41 -> 1900.7941 | U41: =+T41/M41 -> 0.41310476 | V41: =+T41*U41 -> 785.2271
A42: 46 | B42: 2 | C42: Base A4 | D42: 22792669933 | E42: 1 Base de corte A4 Silhouette Portrait 1, 2, 3 - Cameo 2 e 3 - Transparente - Com Cola [4] | F42: 29554 | G42: 664 | H42: 2.25% | I42: 100 | J42: 1.72 | K42: 15.06% | L42: 104 | M42: 2377.81 | N42: 172.23 | O42: 7.24% | P42: Base de Corte | Q42: A4 | R42: 1 | S42: 0.38517754 | T42: =+S42*M42 -> 915.879 | U42: =+T42/M42 -> 0.38517754 | V42: =+T42*U42 -> 352.77602
A43: 47 | B43: 2 | C43: Base A4 | D43: 22592838545 | E43: Kit 4 Bases de Corte A4 Transparente Compativel Cameo 1, 2, 3, 4 e 5 - Com Cola 20,3cm x 30,5cm [3] | F43: 25125 | G43: 409 | H43: 1.63% | I43: 41 | J43: 4.16 | K43: 10.02% | L43: 41 | M43: 2363.39 | N43: 170.57 | O43: 7.22% | P43: Base de Corte | Q43: A4 | R43: 4 | S43: 0.37602001 | T43: =+S43*M43 -> 888.68192 | U43: =+T43/M43 -> 0.37602001 | V43: =+T43*U43 -> 334.16218
A44: 48 | B44: 2 | C44: Base A4 | D44: 22792781219 | E44: 2 Base de Corte A4 - Linha Pro Com Cola - Compativel Silhouette Portrait - Cameo [4] | F44: 21841 | G44: 339 | H44: 1.55% | I44: 18 | J44: 4.54 | K44: 5.31% | L44: 19 | M44: 771.55 | N44: 81.78 | O44: 10.60% | P44: Base de Corte | Q44: A4 | R44: 2 | S44: 0.40691701 | T44: =+S44*M44 -> 313.95682 | U44: =+T44/M44 -> 0.40691701 | V44: =+T44*U44 -> 127.75437
A45: 56 | B45: 2 | C45: Base A4 | D45: 22697277401 | E45: Kit 2 Bases de Corte Transparente A4 Para Silhouette Portrait, Portrait 2, 3 - Cameo 2 e 3 - Com Cola [4] | F45: 11619 | G45: 165 | H45: 1.42% | I45: 19 | J45: 3.04 | K45: 11.52% | L45: 19 | M45: 624.1 | N45: 57.8 | O45: 9.26% | P45: Base de Corte | Q45: A4 | R45: 2 | S45: 0.40691701 | T45: =+S45*M45 -> 253.9569 | U45: =+T45/M45 -> 0.40691701 | V45: =+T45*U45 -> 103.33938
A46: 59 | B46: 2 | C46: Base A4 | D46: 18697607826 | E46: 2 Base de Corte A4 Transparente + 1 Tubo de Cola Para Reposição - Para Silhouette Portrait e Cameo [4] | F46: 9751 | G46: 94 | H46: 0.96% | I46: 5 | J46: 6.05 | K46: 5.32% | L46: 5 | M46: 299.5 | N46: 30.27 | O46: 10.11% | P46: Base de Corte | Q46: A4 | R46: 2 | S46: 0.40691701 | T46: =+S46*M46 -> 121.87164 | U46: =+T46/M46 -> 0.40691701 | V46: =+T46*U46 -> 49.591644
A47: 60 | B47: 2 | C47: Base A4 | D47: 23898758222 | E47: 2 Bases de Corte A4 Portrait + 2 Bases A4 Paisagem com cola | F47: 8987 | G47: 122 | H47: 1.36% | I47: 1 | J47: 47.17 | K47: 0.82% | L47: 1 | M47: 68.9 | N47: 47.17 | O47: 68.46% | P47: Base de Corte | Q47: A4 | R47: 2 | S47: 0.40691701 | T47: =+S47*M47 -> 28.036582 | U47: =+T47/M47 -> 0.40691701 | V47: =+T47*U47 -> 11.408562
A48: 61 | B48: 2 | C48: Base A4 | D48: 19897609772 | E48: Kit 2 Base de Corte A4 Transparente + 1 Cola Para Reposição 50g - Compatível Com Silhouette Portrait E Cameo [4] | F48: 8250 | G48: 79 | H48: 0.96% | I48: 1 | J48: 12.79 | K48: 1.27% | L48: 1 | M48: 59.9 | N48: 12.79 | O48: 21.35% | P48: Base de Corte | Q48: A4 | R48: 2 | S48: 0.40691701 | T48: =+S48*M48 -> 24.374329 | U48: =+T48/M48 -> 0.40691701 | V48: =+T48*U48 -> 9.9183288
A49: 67 | B49: 2 | C49: Base A4 | D49: 23792775950 | E49: 4 Base de Corte A4 Transparente +1 Cola 50g Compativel Silhouette Portrait 2 e 3 -Com Cola [5] | F49: 5318 | G49: 28 | H49: 0.53% | I49: 1 | J49: 13.38 | K49: 3.57% | L49: 1 | M49: 85.9 | N49: 13.38 | O49: 15.58% | P49: Base de Corte | Q49: A4 | R49: 4 | S49: 0.37602001 | T49: =+S49*M49 -> 32.300119 | U49: =+T49/M49 -> 0.37602001 | V49: =+T49*U49 -> 12.145491
A50: 79 | B50: 3 | C50: Base A4 | D50: 22792693512 | E50: Kit 2 Base de Corte A4 Transparente Silhouette - Cameo 2, 3, 4 - Com Cola [3] | F50: 11470 | G50: 246 | H50: 2.14% | I50: 20 | J50: 3.64 | K50: 0.0813 | L50: 20 | M50: 766.6 | N50: 72.8 | O50: 0.095 | P50: Base de Corte | Q50: A4 | R50: 2 | S50: 0.40691701 | T50: =+S50*M50 -> 311.94258 | U50: =+T50/M50 -> 0.40691701 | V50: =+T50*U50 -> 126.93474
A51: 81 | B51: 3 | C51: Base A4 | D51: 23829845447 | E51: Kit 2 Base de Corte Transparente A4 Retrato - Silhouette Portrait 1, 2 e 3 [5] | F51: 41107 | G51: 826 | H51: 2.01% | I51: 108 | J51: 3.41 | K51: 0.1308 | L51: 109 | M51: 3750.68 | N51: 368.51 | O51: 0.0983 | P51: Base de Corte | Q51: A4 | R51: 2 | S51: 0.40691701 | T51: =+S51*M51 -> 1526.2155 | U51: =+T51/M51 -> 0.40691701 | V51: =+T51*U51 -> 621.04303
A52: 82 | B52: 3 | C52: Base A4 | D52: 22792693513 | E52: Kit 2 Base de Corte Transparente A4 Silhouette Portrait 2, 3 e 4 Com Cola [2] | F52: 10457 | G52: 203 | H52: 1.94% | I52: 6 | J52: 4.02 | K52: 0.0296 | L52: 6 | M52: 221.4 | N52: 24.14 | O52: 0.1091 | P52: Base de Corte | Q52: A4 | R52: 2 | S52: 0.40691701 | T52: =+S52*M52 -> 90.091425 | U52: =+T52/M52 -> 0.40691701 | V52: =+T52*U52 -> 36.659733
A53: 84 | B53: 3 | C53: Base A4 | D53: 22492098258 | E53: Kit 4 Base de Corte A4 (com Cola) Compatível Silhouette Portrait 1 à 4 + Liner Protetor [4] | F53: 16293 | G53: 253 | H53: 1.55% | I53: 23 | J53: 5.5 | K53: 0.0909 | L53: 24 | M53: 1370.66 | N53: 126.58 | O53: 0.0924 | P53: Base de Corte | Q53: A4 | R53: 4 | S53: 0.37602001 | T53: =+S53*M53 -> 515.39558 | U53: =+T53/M53 -> 0.37602001 | V53: =+T53*U53 -> 193.79905
A54: 86 | B54: 3 | C54: Base A4 | D54: 23497184477 | E54: Kit 4 Base de Corte A4 Retrato - Transparente Compativel Silhouette Portrait e Cameo - Com Cola [2] | F54: 112173 | G54: 2219 | H54: 1.98% | I54: 280 | J54: 4.34 | K54: 0.1262 | L54: 291 | M54: 15959.34 | N54: 1213.83 | O54: 0.0761 | P54: Base de Corte | Q54: A4 | R54: 4 | S54: 0.37602001 | T54: =+S54*M54 -> 6001.0311 | U54: =+T54/M54 -> 0.37602001 | V54: =+T54*U54 -> 2256.5078
A55: 87 | B55: 3 | C55: Base A4 | D55: 18799097725 | E55: Kit 4 Base de Corte A4 Transparente Compativel Silhouette Portrait 1,2 e 3 -Com Cola [2] | F55: 14688 | G55: 243 | H55: 1.65% | I55: 27 | J55: 5.06 | K55: 0.1111 | L55: 27 | M55: 1455.96 | N55: 136.59 | O55: 0.0938 | P55: Base de Corte | Q55: A4 | R55: 4 | S55: 0.37602001 | T55: =+S55*M55 -> 547.47009 | U55: =+T55/M55 -> 0.37602001 | V55: =+T55*U55 -> 205.85971
A56: 88 | B56: 3 | C56: Base A4 | D56: 18799097700 | E56: Kit 4 Base de Corte Transparente A4 Retrato - Silhouette Portrait 2, 3 e 4 - Com Cola [4] | F56: 8676 | G56: 78 | H56: 0.0009 | I56: 4 | J56: 8.23 | K56: 0.0513 | L56: 5 | M56: 308.3 | N56: 32.9 | O56: 0.1067 | P56: Base de Corte | Q56: A4 | R56: 4 | S56: 0.37602001 | T56: =+S56*M56 -> 115.92697 | U56: =+T56/M56 -> 0.37602001 | V56: =+T56*U56 -> 43.590859
A57: 89 | B57: 3 | C57: Base A4 | D57: 28794280797 | E57: Kit 5 Base de Corte A4 Retrato com Cola Portrait 4 | para Topo de Bolo e Papelaria Criativa | F57: 2934 | G57: 33 | H57: 1.12% | I57: 0 | J57: 0 | K57: 0 | L57: 0 | M57: 0 | N57: 14.92 | O57: 0 | P57: Base de Corte | Q57: A4 | R57: 5 | S57: 0.46116061 | T57: =+S57*M57 -> 0 | U57: =+T57/M57 -> #DIV/0! | V57: =+T57*U57 -> #DIV/0!
A58: 54 | B58: 2 | C58: Base A4 | D58: 22197175859 | E58: Base de corte para Silhouette Portrait A4 - 250 Microns Espessura Original - Transparente - Com Cola [3] | F58: 13143 | G58: 306 | H58: 2.33% | I58: 35 | J58: 2.42 | K58: 11.44% | L58: 36 | M58: 930.49 | N58: 84.64 | O58: 9.10% | P58: Base de Corte | Q58: A4 | R58: 1 | S58: 0.38517754 | T58: =+S58*M58 -> 358.40385 | U58: =+T58/M58 -> 0.38517754 | V58: =+T58*U58 -> 138.04911
A59: 85 | B59: 3 | C59: Base A4P | D59: 21697638799 | E59: Kit 4 Base de Corte A4 Paisagem TRANSPARENTE (Com Cola) Silhouette Cameo Alta Rigidez [4] | F59: 69645 | G59: 1063 | H59: 1.53% | I59: 114 | J59: 4.89 | K59: 0.1072 | L59: 118 | M59: 6730.62 | N59: 557.58 | O59: 0.0828 | P59: Base de Corte | Q59: A4 | R59: 4 | S59: 0.37602001 | T59: =+S59*M59 -> 2530.8478 | U59: =+T59/M59 -> 0.37602001 | V59: =+T59*U59 -> 951.6494
A60: 13 | B60: 1 | C60: Base A4P | D60: 22097387599 | E60: Base de Corte Paisagem COMPATIVEL Silhouette Cameo, Cameo 1, 2, 3 E 4 - Com Cola | F60: 15545 | G60: 410 | H60: 0.0264 | I60: 38 | J60: 2.3 | K60: 0.0927 | L60: 42 | M60: 919.4 | N60: 87.23 | O60: 0.0949 | P60: Base de Corte | Q60: A4 Paisagem | R60: 1 | S60: 0.36158546 | T60: =+S60*M60 -> 332.44168 | U60: =+T60/M60 -> 0.36158546 | V60: =+T60*U60 -> 120.20608
A61: 24 | B61: 1 | C61: Base A4P | D61: 23393517180 | E61: KIT 4 Base de Corte A4 Paisagem + Cola de Reposição Para Base 50g - Silhouette Portrait e Cameo | F61: 6620 | G61: 77 | H61: 0.0116 | I61: 4 | J61: 10.16 | K61: 0.0519 | L61: 4 | M61: 292.6 | N61: 40.63 | O61: 0.1388 | P61: Base de Corte | Q61: A4 Paisagem | R61: 4 | S61: 0.37179327 | T61: =+S61*M61 -> 108.78671 | U61: =+T61/M61 -> 0.37179327 | V61: =+T61*U61 -> 40.446167
A62: 76 | B62: 3 | C62: Base Joy | D62: 58251764221 | E62: Base de Corte Power Film Compatível Cricut Joy mini - 1un | F62: 9228 | G62: 95 | H62: 1.03% | I62: 2 | J62: 13.1 | K62: 0.0211 | L62: 2 | M62: 82.79 | N62: 26.19 | O62: 0.3164 | P62: Base de Corte | Q62: Joy Mini | R62: 1 | S62: 0.16318619 | T62: =+S62*M62 -> 13.510185 | U62: =+T62/M62 -> 0.16318619 | V62: =+T62*U62 -> 2.2046755
A63: 78 | B63: 3 | C63: Base Joy | D63: 22194735251 | E63: Kit 2 Base De Corte Power Film Compatível Cricut Joy Mini 11,5 x 30,5 cm | F63: 5238 | G63: 33 | H63: 0.63% | I63: 0 | J63: 0 | K63: 0 | L63: 0 | M63: 0 | N63: 8.39 | O63: 0 | P63: Base de Corte | Q63: Joy Mini | R63: 2 | S63: 0.18643613 | T63: =+S63*M63 -> 0 | U63: =+T63/M63 -> #DIV/0! | V63: =+T63*U63 -> #DIV/0!
A64: 22 | B64: 1 | C64: Base P4 | D64: 19899863668 | E64: Kit 2 Base de Corte Transparente com Cola - A4 Portrait 4 - 250 micras Resistente | F64: 4167 | G64: 35 | H64: 0.0084 | I64: 1 | J64: 11.07 | K64: 0.0286 | L64: 1 | M64: 56.9 | N64: 11.07 | O64: 0.1946 | P64: Base de Corte | Q64: Portrait 4 | R64: 2 | S64: 0.17666957 | T64: =+S64*M64 -> 10.052498 | U64: =+T64/M64 -> 0.17666957 | V64: =+T64*U64 -> 1.7759705
A65: 49 | B65: 2 | C65: Base P4 | D65: 22194374055 | E65: Kit 3 Bases de Corte Com Cola A4 para Portrait 4 | F65: 18727 | G65: 325 | H65: 1.74% | I65: 13 | J65: 13.71 | K65: 4.00% | L65: 13 | M65: 819.7 | N65: 178.26 | O65: 21.75% | P65: Base de Corte | Q65: Portrait 4 | R65: 3 | S65: 0.26393805 | T65: =+S65*M65 -> 216.35002 | U65: =+T65/M65 -> 0.26393805 | V65: =+T65*U65 -> 57.103
A66: 63 | B66: 2 | C66: Base P4 | D66: 22198866258 | E66: Kit 2 Base de Corte Compativel Portrait 4 - com Cola | F66: 7187 | G66: 84 | H66: 1.17% | I66: 3 | J66: 32.23 | K66: 3.57% | L66: 3 | M66: 169.7 | N66: 96.68 | O66: 56.97% | P66: Base de Corte | Q66: Portrait 4 | R66: 2 | S66: 0.17666957 | T66: =+S66*M66 -> 29.980826 | U66: =+T66/M66 -> 0.17666957 | V66: =+T66*U66 -> 5.2966995
A67: 64 | B67: 2 | C67: Base P4 | D67: 27542190442 | E67: Kit 2 Bases de Corte Portrait 4 + Cola 50g - Linha Pro | F67: 6534 | G67: 99 | H67: 1.52% | I67: 2 | J67: 16.09 | K67: 2.02% | L67: 2 | M67: 107.8 | N67: 32.18 | O67: 29.85% | P67: Base de Corte | Q67: Portrait 4 | R67: 2 | S67: 0.17666957 | T67: =+S67*M67 -> 19.044979 | U67: =+T67/M67 -> 0.17666957 | V67: =+T67*U67 -> 3.3646683
A68: 65 | B68: 2 | C68: Base P4 | D68: 22198870488 | E68: Base De Corte Portrait 4 Transparente + 1 Cola 50g | F68: 6237 | G68: 103 | H68: 1.65% | I68: 3 | J68: 18.89 | K68: 2.91% | L68: 3 | M68: 144.7 | N68: 56.67 | O68: 39.16% | P68: Base de Corte | Q68: Portrait 4 | R68: 1 | S68: 0.3 | T68: =+S68*M68 -> 43.41 | U68: =+T68/M68 -> 0.3 | V68: =+T68*U68 -> 13.023
A69: 66 | B69: 2 | C69: Base P4 | D69: 28642190464 | E69: 4 Bases De Corte Com cola A4 para Portrait 4 | F69: 8883 | G69: 84 | H69: 0.95% | I69: 0 | J69: 0 | K69: 0.00% | L69: 0 | M69: 0 | N69: 72.85 | O69: 0.00% | P69: Base de Corte | Q69: Portrait 4 | R69: 4 | S69: 0.3 | T69: =+S69*M69 -> 0 | U69: =+T69/M69 -> #DIV/0! | V69: =+T69*U69 -> #DIV/0!
A70: 72 | B70: 3 | C70: Base P4 | D70: 51956439915 | E70: 3 Base de Corte para Portrait 4 Compatível Silhouette | F70: 9876 | G70: 169 | H70: 1.71% | I70: 8 | J70: 8.44 | K70: 0.0473 | L70: 8 | M70: 495.2 | N70: 67.53 | O70: 0.1364 | P70: Base de Corte | Q70: Portrait 4 | R70: 3 | S70: 0.26393805 | T70: =+S70*M70 -> 130.70212 | U70: =+T70/M70 -> 0.26393805 | V70: =+T70*U70 -> 34.497262
A71: 74 | B71: 3 | C71: Base P4 | D71: 45257455937 | E71: Base de Corte Compatível Silhouette Portrait 4 com Cola - Kit com 2 [2] | F71: 25084 | G71: 585 | H71: 2.33% | I71: 19 | J71: 8.27 | K71: 0.0325 | L71: 21 | M71: 1054.95 | N71: 157.19 | O71: 0.149 | P71: Base de Corte | Q71: Portrait 4 | R71: 2 | S71: 0.17666957 | T71: =+S71*M71 -> 186.37756 | U71: =+T71/M71 -> 0.17666957 | V71: =+T71*U71 -> 32.927243
A72: 80 | B72: 3 | C72: Base P4 | D72: 22194438407 | E72: Kit 2 Base de Corte Portrait 4 (Com Cola) | F72: 8837 | G72: 174 | H72: 1.97% | I72: 8 | J72: 9.99 | K72: 0.046 | L72: 9 | M72: 478.4 | N72: 79.94 | O72: 0.1671 | P72: Base de Corte | Q72: Portrait 4 | R72: 2 | S72: 0.17666957 | T72: =+S72*M72 -> 84.518721 | U72: =+T72/M72 -> 0.17666957 | V72: =+T72*U72 -> 14.931886
A73: 83 | B73: 3 | C73: Base P4 | D73: 23194341263 | E73: Kit 3 Base de Corte A4 para Portrait 4 - TRANSPARENTE Papelaria Silhouette Esteira de corte - Com cola | F73: 2983 | G73: 31 | H73: 1.04% | I73: 4 | J73: 1.84 | K73: 0.129 | L73: 4 | M73: 357.59 | N73: 7.35 | O73: 0.0206 | P73: Base de Corte | Q73: Portrait 4 | R73: 3 | S73: 0.26393805 | T73: =+S73*M73 -> 94.381606 | U73: =+T73/M73 -> 0.26393805 | V73: =+T73*U73 -> 24.910896
A74: 75 | B74: 3 | C74: Base Xtra | D74: 50807158309 | E74: Base de Corte Power Film Com cola Compativel com CRICUT JOY XTRA | F74: 18025 | G74: 374 | H74: 2.07% | I74: 35 | J74: 3.83 | K74: 0.0936 | L74: 35 | M74: 1405.5 | N74: 134.1 | O74: 0.0954 | P74: Base de Corte | Q74: Joy Xtra | R74: 1 | S74: 0.2010742 | T74: =+S74*M74 -> 282.60978 | U74: =+T74/M74 -> 0.2010742 | V74: =+T74*U74 -> 56.825535
A75: 16 | B75: 1 | C75: Cola | D75: 19799037778 | E75: Cola para Base de Corte Silhouette e ScanNCut - Permanente - Fácil Aplicação - Reposição - 50g | F75: 11558 | G75: 128 | H75: 0.0111 | I75: 18 | J75: 3.06 | K75: 0.1406 | L75: 19 | M75: 684.15 | N75: 55.04 | O75: 0.0804 | P75: Base de Corte | Q75: Cola 50g | R75: 1 | S75: 0.36913205 | T75: =+S75*M75 -> 252.54169 | U75: =+T75/M75 -> 0.36913205 | V75: =+T75*U75 -> 93.221232
A76: 53 | B76: 2 | C76: Cola | D76: 22197175015 | E76: Cola Para Reposição de Base de Corte 50g - PARA TODOS OS MODELOS DE BASES#UNIVERSAL [4] | F76: 13813 | G76: 181 | H76: 1.31% | I76: 11 | J76: 7.74 | K76: 6.08% | L76: 11 | M76: 456.9 | N76: 85.19 | O76: 18.64% | P76: Base de Corte | Q76: Cola 50g | R76: 1 | S76: 0.36913205 | T76: =+S76*M76 -> 168.65643 | U76: =+T76/M76 -> 0.36913205 | V76: =+T76*U76 -> 62.256495
A77: 29 | B77: 1 | C77: QC 10 | D77: 23795681999 | E77: Conjunto 10 Quebra Cabeças Diferentes - Era dos Dinossauros - 60 Peças Cada Um | F77: 139914 | G77: 5112 | H77: 0.0365 | I77: 199 | J77: 4.26 | K77: 0.0389 | L77: 201 | M77: 12972.07 | N77: 847.16 | O77: 0.0653 | P77: Quebra Cabeça | Q77: Único | R77: 10 | S77: 0.28145739 | T77: =+S77*M77 -> 3651.085 | U77: =+T77/M77 -> 0.28145739 | V77: =+T77*U77 -> 1027.6248
A78: 30 | B78: 1 | C78: QC 10 | D78: 22797389671 | E78: Quebra Cabeça Kit Com 10 Modelos Mundo Animal VOL 1 e 2 | F78: 133588 | G78: 3611 | H78: 0.027 | I78: 116 | J78: 5.02 | K78: 0.0321 | L78: 119 | M78: 7845.79 | N78: 581.92 | O78: 0.0742 | P78: Quebra Cabeça | Q78: Único | R78: 10 | S78: 0.28145739 | T78: =+S78*M78 -> 2208.2556 | U78: =+T78/M78 -> 0.28145739 | V78: =+T78*U78 -> 621.52985
A79: 31 | B79: 1 | C79: QC 10 | D79: 22497100149 | E79: 10 Quebra-Cabeças Bíblicos - Cada Puzzle com 60 Peças e Caixa Especial | F79: 114154 | G79: 3012 | H79: 0.0264 | I79: 119 | J79: 4.13 | K79: 0.0395 | L79: 120 | M79: 7706.9 | N79: 491.58 | O79: 0.0638 | P79: Quebra Cabeça | Q79: Único | R79: 10 | S79: 0.28145739 | T79: =+S79*M79 -> 2169.164 | U79: =+T79/M79 -> 0.28145739 | V79: =+T79*U79 -> 610.52722
A80: 32 | B80: 1 | C80: QC 10 | D80: 22497100181 | E80: 10 Puzzles Inspirados em Contos de Fada - 60 Peças por Quebra-Cabeça com Embalagem Exclusiva | F80: 35545 | G80: 1146 | H80: 0.0322 | I80: 37 | J80: 4.85 | K80: 0.0323 | L80: 38 | M80: 2451.2 | N80: 179.39 | O80: 0.0732 | P80: Quebra Cabeça | Q80: Único | R80: 10 | S80: 0.28145739 | T80: =+S80*M80 -> 689.90835 | U80: =+T80/M80 -> 0.28145739 | V80: =+T80*U80 -> 194.1798
A81: 33 | B81: 1 | C81: QC 10 | D81: 22497100169 | E81: 10 Quebra-Cabeças bíblicos - 60 Peças por Puzzle - Maleta personalizada - Especial Escola Dominical | F81: 34495 | G81: 767 | H81: 0.0222 | I81: 22 | J81: 5.1 | K81: 0.0287 | L81: 22 | M81: 1433.16 | N81: 112.15 | O81: 0.0783 | P81: Quebra Cabeça | Q81: Único | R81: 10 | S81: 0.28145739 | T81: =+S81*M81 -> 403.37347 | U81: =+T81/M81 -> 0.28145739 | V81: =+T81*U81 -> 113.53244
A82: 34 | B82: 1 | C82: QC 10 | D82: 22528314756 | E82: Kit 10 Quebra-Cabeças Infantil Educativo | Especial Escola Dominical | 60 Peças Cada | Aprendizado | F82: 29409 | G82: 522 | H82: 0.0177 | I82: 14 | J82: 7.54 | K82: 0.0268 | L82: 14 | M82: 947.6 | N82: 105.59 | O82: 0.1114 | P82: Quebra Cabeça | Q82: Único | R82: 10 | S82: 0.28145739 | T82: =+S82*M82 -> 266.70902 | U82: =+T82/M82 -> 0.28145739 | V82: =+T82*U82 -> 75.067225
A83: 35 | B83: 1 | C83: QC 10 | D83: 18976211935 | E83: Quebra Cabeça - Kit Com 10 Modelos - Dinossauros | F83: 17355 | G83: 407 | H83: 0.0235 | I83: 19 | J83: 5.51 | K83: 0.0467 | L83: 19 | M83: 1014 | N83: 104.62 | O83: 0.0939 | P83: Quebra Cabeça | Q83: Único | R83: 10 | S83: 0.28145739 | T83: =+S83*M83 -> 285.39779 | U83: =+T83/M83 -> 0.28145739 | V83: =+T83*U83 -> 80.327317
A84: 37 | B84: 1 | C84: QC 10 | D84: 18321126663 | E84: Kit 10 Quebra Cabeças - Era dos Dinossauros e outros temas ESCOLHA - 60 Peças Cada | F84: 23004 | G84: 357 | H84: 0.0155 | I84: 15 | J84: 5.03 | K84: 0.042 | L84: 15 | M84: 1113.8 | N84: 75.44 | O84: 0.0763 | P84: Quebra Cabeça | Q84: Único | R84: 10 | S84: 0.28145739 | T84: =+S84*M84 -> 313.48724 | U84: =+T84/M84 -> 0.28145739 | V84: =+T84*U84 -> 88.2333
A85: 38 | B85: 1 | C85: QC 10 | D85: 22992892990 | E85: Kit 10 Quebra Cabeça Infantil Mundo Animal Colorido VOL 5 e 6 | F85: 13737 | G85: 267 | H85: 0.0194 | I85: 13 | J85: 5.72 | K85: 0.0487 | L85: 13 | M85: 876.7 | N85: 74.41 | O85: 0.0849 | P85: Quebra Cabeça | Q85: Único | R85: 10 | S85: 0.28145739 | T85: =+S85*M85 -> 246.75369 | U85: =+T85/M85 -> 0.28145739 | V85: =+T85*U85 -> 69.45065
A86: 93 | B86: 3 | C86: QC 10 | D86: 22695573910 | E86: Kit 10 Quebra Cabeça Infantil - Dinossauros - Brinquedo de Montar Educativo [5] | F86: 23582 | G86: 466 | H86: 1.98% | I86: 18 | J86: 6.54 | K86: 0.0386 | L86: 19 | M86: 1160.74 | N86: 117.75 | O86: 0.1014 | P86: Quebra Cabeça | Q86: Único | R86: 10 | S86: 0.28145739 | T86: =+S86*M86 -> 326.69885 | U86: =+T86/M86 -> 0.28145739 | V86: =+T86*U86 -> 91.951805
A87: 94 | B87: 3 | C87: QC 10 | D87: 23997394407 | E87: Kit 10 Quebra Cabeça Infantil Animal – 600 Peças – Brinquedo Educativo [3] | F87: 151144 | G87: 3596 | H87: 2.38% | I87: 127 | J87: 4.64 | K87: 0.0353 | L87: 131 | M87: 8952.21 | N87: 589.32 | O87: 0.0658 | P87: Quebra Cabeça | Q87: Único | R87: 10 | S87: 0.28145739 | T87: =+S87*M87 -> 2519.6657 | U87: =+T87/M87 -> 0.28145739 | V87: =+T87*U87 -> 709.17852
A88: 95 | B88: 3 | C88: QC 10 | D88: 22395579066 | E88: Kit 10 Quebra Cabeças Infantil Dinossauros 60 Peças Cada - Brinquedo Educativo [3] | F88: 13839 | G88: 329 | H88: 2.38% | I88: 11 | J88: 6.39 | K88: 0.0334 | L88: 11 | M88: 724.48 | N88: 70.26 | O88: 0.097 | P88: Quebra Cabeça | Q88: Único | R88: 10 | S88: 0.28145739 | T88: =+S88*M88 -> 203.91025 | U88: =+T88/M88 -> 0.28145739 | V88: =+T88*U88 -> 57.392046
A89: 96 | B89: 3 | C89: QC 3 | D89: 22197320073 | E89: Kit 3 Quebra Cabeça - Dinossauros Vol 3 60 Peças Cada - infantil Dinos - Brinquedo de Montar [2] | F89: 12211 | G89: 236 | H89: 1.93% | I89: 9 | J89: 7.08 | K89: 0.0381 | L89: 10 | M89: 498.03 | N89: 63.72 | O89: 0.1279 | P89: Quebra Cabeça | Q89: Único | R89: 3 | S89: 0.38237345 | T89: =+S89*M89 -> 190.43345 | U89: =+T89/M89 -> 0.38237345 | V89: =+T89*U89 -> 72.816696
A90: 97 | B90: 3 | C90: QC 3 | D90: 23697389359 | E90: Kit 3 Quebra-cabeça Infantil Gatinhos Fofos Colorido Educativo Dia das Crianças | F90: 8100 | G90: 127 | H90: 1.57% | I90: 0 | J90: 0 | K90: 0 | L90: 0 | M90: 0 | N90: 7.44 | O90: 0 | P90: Quebra Cabeça | Q90: Único | R90: 3 | S90: 0.38237345 | T90: =+S90*M90 -> 0 | U90: =+T90/M90 -> #DIV/0! | V90: =+T90*U90 -> #DIV/0!
A91: 36 | B91: 1 | C91: QC 5 | D91: 21573674223 | E91: 5 Quebra Cabeça Educativo Infantil - Kit Bíblico - Vol 1 | F91: 26794 | G91: 581 | H91: 0.0217 | I91: 20 | J91: 4.45 | K91: 0.0344 | L91: 20 | M91: 988.43 | N91: 89.08 | O91: 0.0878 | P91: Quebra Cabeça | Q91: Único | R91: 5 | S91: 0.34331499 | T91: =+S91*M91 -> 339.34283 | U91: =+T91/M91 -> 0.34331499 | V91: =+T91*U91 -> 116.50148
A92: 91 | B92: 3 | C92: QC 5 | D92: 23792918193 | E92: Combo 5 Quebra Cabeças Infantil Mundo Animal Vol 1 - 60 Peças Cada - Leve 5 - Presente de Aniversário [2] | F92: 46939 | G92: 1210 | H92: 2.58% | I92: 60 | J92: 3.87 | K92: 0.0496 | L92: 62 | M92: 3031.8 | N92: 232.34 | O92: 0.0766 | P92: Quebra Cabeça | Q92: Único | R92: 5 | S92: 0.34331499 | T92: =+S92*M92 -> 1040.8624 | U92: =+T92/M92 -> 0.34331499 | V92: =+T92*U92 -> 357.34366
A93: 92 | B93: 3 | C93: QC 5 | D93: 20699227781 | E93: Kit 10 Quebra Cabeça - Animais - Vol 5 - Para Presente Educativo Clássicos Puzzle Presente de Natal [4] | F93: 21051 | G93: 575 | H93: 2.73% | I93: 22 | J93: 4.19 | K93: 0.0383 | L93: 24 | M93: 1220.33 | N93: 92.28 | O93: 0.0756 | P93: Quebra Cabeça | Q93: Único | R93: 10 | S93: 0.28145739 | T93: =+S93*M93 -> 343.4709 | U93: =+T93/M93 -> 0.28145739 | V93: =+T93*U93 -> 96.672421
A94: 98 | B94: 3 | C94: QC 5 | D94: 23797452997 | E94: Kit 5 Quebra Cabeça Infantil Histórias Evangélicas Vol 2 jogos educativos dia das crianças presente [2] | F94: 18843 | G94: 392 | H94: 2.08% | I94: 17 | J94: 4.18 | K94: 0.0434 | L94: 17 | M94: 760.3 | N94: 71.12 | O94: 0.0935 | P94: Quebra Cabeça | Q94: Único | R94: 5 | S94: 0.34331499 | T94: =+S94*M94 -> 261.02239 | U94: =+T94/M94 -> 0.34331499 | V94: =+T94*U94 -> 89.612898
A95: 99 | B95: 3 | C95: QC 5 | D95: 23896708715 | E95: Kit 5 Quebra Cabeça Infantil Tema História Clássica Infantil 60 Peças cada - Jogo Educativo [5] | F95: 6338 | G95: 147 | H95: 2.32% | I95: 1 | J95: 28.56 | K95: 0.0068 | L95: 1 | M95: 59.9 | N95: 28.56 | O95: 0.4767 | P95: Quebra Cabeça | Q95: Único | R95: 5 | S95: 0.34331499 | T95: =+S95*M95 -> 20.564568 | U95: =+T95/M95 -> 0.34331499 | V95: =+T95*U95 -> 7.0601244
A96: 100 | B96: 3 | C96: QC 5 | D96: 19699233607 | E96: Kit 5 Quebra Cabeças - 60 Peças Cada - Mundo Animal Vol 5 - Brinquedo Infantil Educativo [2] | F96: 10510 | G96: 257 | H96: 2.45% | I96: 18 | J96: 3.52 | K96: 0.07 | L96: 18 | M96: 880.2 | N96: 63.45 | O96: 0.0721 | P96: Quebra Cabeça | Q96: Único | R96: 5 | S96: 0.34331499 | T96: =+S96*M96 -> 302.18585 | U96: =+T96/M96 -> 0.34331499 | V96: =+T96*U96 -> 103.74493
A97: 101 | B97: 3 | C97: QC 5 | D97: 22397421387 | E97: Kit 5 Quebra Cabeças 60 Peças - Mundo Animal Vol 2 Brinquedos educativos Bichos Dia das Crianças [2] | F97: 40123 | G97: 1323 | H97: 0.33% | I97: 55 | J97: 3.81 | K97: 0.0416 | L97: 56 | M97: 2755.51 | N97: 209.34 | O97: 0.076 | P97: Quebra Cabeça | Q97: Único | R97: 5 | S97: 0.34331499 | T97: =+S97*M97 -> 946.00789 | U97: =+T97/M97 -> 0.34331499 | V97: =+T97*U97 -> 324.77869
A98: 102 | B98: 3 | C98: QC 5 | D98: 23797453001 | E98: Kit 5 Quebra Cabeças Infantil Histórias Bíblicas Educativas Cristão Vol 2 - 60 Peças cada [2] | F98: 180331 | G98: 5138 | H98: 2.85% | I98: 251 | J98: 2.9 | K98: 0.0489 | L98: 255 | M98: 10733.43 | N98: 728.26 | O98: 0.0679 | P98: Quebra Cabeça | Q98: Único | R98: 5 | S98: 0.34331499 | T98: =+S98*M98 -> 3684.9474 | U98: =+T98/M98 -> 0.34331499 | V98: =+T98*U98 -> 1265.0977
A99: 103 | B99: 3 | C99: QC 5 | D99: 19197628112 | E99: Kit 5 Quebra-Cabeças de Dinossauros para Crianças – 60 Peças – Colorido, Divertido e Educativo [2] | F99: 120719 | G99: 3283 | H99: 2.72% | I99: 148 | J99: 3.17 | K99: 0.0451 | L99: 151 | M99: 7050.08 | N99: 469.67 | O99: 0.0666 | P99: Quebra Cabeça | Q99: Único | R99: 5 | S99: 0.34331499 | T99: =+S99*M99 -> 2420.3981 | U99: =+T99/M99 -> 0.34331499 | V99: =+T99*U99 -> 830.95896
A100: 90 | B100: 3 | C100: QC Branco | D100: 22896684408 | E100: 10 Quebra Cabeça Branco Para Sublimação - 60 Peças Cada [3] | F100: 74688 | G100: 1280 | H100: 1.71% | I100: 41 | J100: 6.69 | K100: 0.032 | L100: 68 | M100: 3467.41 | N100: 274.49 | O100: 0.0792 | P100: Quebra Cabeça para Sublimação | Q100: Único | R100: 10 | S100: 0.31743086 | T100: =+S100*M100 -> 1100.6629 | U100: =+T100/M100 -> 0.31743086 | V100: =+T100*U100 -> 349.38438
...

Sheet Resumo
A1: Resumo - Base e Esteira de Corte
A3: Anúncios filtrados | C3: =COUNTA('Base e QC'!D2:D29) -> 28
A4: Investimento (Despesas) | C4: =SUM('Base e QC'!N2:N29) -> 2737.85
A5: GMV | C5: =SUM('Base e QC'!M2:M29) -> 36033.13
A6: ROAS médio ponderado | C6: =IFERROR(C5/C4,0) -> 13.161105
A7: ACOS médio ponderado | C7: =IFERROR(C4/C5,0) -> 0.075981465
A8: Cliques | C8: =SUM('Base e QC'!G2:G29) -> 8347
A9: Conversões | C9: =SUM('Base e QC'!I2:I29) -> 740
A10: CTR médio ponderado | C10: =IFERROR(C8/C11,0) -> 0.021144279
A11: Impressões | C11: =SUM('Base e QC'!F2:F29) -> 394764
A13: ID do Anúncio | B13: Nome do Anúncio | C13: GMV | D13: Despesas | E13: ROAS | F13: ACOS | G13: Cliques | H13: Conversões
A14: 20997495265 | B14: Kit 4 Base de Corte A4 Transparente 1 Cola 50g Silhouette Portrait 2, 3 e 4 Papelaria e Escritório [2] | C14: 4349 | D14: 297.24 | E14: 14.63 | F14: 0.0683 | G14: 665 | H14: 59
A15: 23697297381 | B15: 2 Base de Corte A4 Transparente +1 Cola Reposição Para Base 50g Para Silhouette Portrait 1,2, 3 e 4 Cameo 2 e 3 Com Cola [3] | C15: 3828.68 | D15: 276.51 | E15: 13.85 | F15: 0.0722 | G15: 653 | H15: 90
A16: 15833567190 | B16: Esteira De Corte 30x30 Para Brother Scanncut CM300, CM550 e CM650 - Envio Imediato! [5] | C16: 2315.9 | D16: 151.02 | E16: 15.33 | F16: 0.0652 | G16: 1114 | H16: 62
A17: 20997495267 | B17: Kit 2 Base de Corte A4 Para Silhouette Portrait 2, 3 e 4 - Cameo, Cameo 2 e 3 - Com Cola [3] | C17: 2304.6 | D17: 157.25 | E17: 14.66 | F17: 0.0682 | G17: 478 | H17: 57
A18: 22694202713 | B18: 2 Bases de Corte A4 Compatível Silhouette Portrait 1,2,3 - Alta Rigidez Com Cola - Cameo | C18: 1791.68 | D18: 132.68 | E18: 13.5 | F18: 0.0741 | G18: 525 | H18: 51
A19: 15250252385 | B19: Base de Corte 30x60 Com Cola para Brother SDX 85, SDX 125 e SDX 225 - Envio Expresso [7] | C19: 1640.2 | D19: 124.13 | E19: 13.21 | F19: 0.0757 | G19: 567 | H19: 36
A20: 23092653852 | B20: Kit 2 Base de Corte 30x30 Transparente Compativel Silhouette, Cameo - Com Cola Alta Fixação [2] | C20: 1297.4 | D20: 75.98 | E20: 17.08 | F20: 0.0586 | G20: 151 | H20: 25
A21: 22097387599 | B21: Base de Corte Paisagem COMPATIVEL Silhouette Cameo, Cameo 1, 2, 3 E 4 - Com Cola [2] | C21: 919.4 | D21: 87.23 | E21: 10.54 | F21: 0.0949 | G21: 410 | H21: 38
A22: 20997495263 | B22: Kit 2 Base de Corte A4 Transparente Silhouette Portrait, Portrait 2, 3 Cameo, Cameo 2 e 3 Com Cola [2] | C22: 729.9 | D22: 58.43 | E22: 12.49 | F22: 0.08 | G22: 176 | H22: 21
A23: 19799037778 | B23: Cola para Base de Corte Silhouette e ScanNCut - Permanente - Fácil Aplicação - Reposição - 50g [2] | C23: 684.15 | D23: 55.04 | E23: 12.43 | F23: 0.0804 | G23: 128 | H23: 18
